superanalysis/__init__.py
superanalysis/version.py
superanalysis/serve/__init__.py
superanalysis/serve/api_server.py
superanalysis/serve/cli.py
superanalysis/serve/convert.py
superanalysis/serve/llm_wrapper.py
superanalysis/serve/openai_serve.py
superanalysis/serve/rest.py
superanalysis/sql/__init__.py
superanalysis/sql/generator.py
superanalysis/sql/types.py
super_analysis-0.1.9.dist-info/METADATA
super_analysis-0.1.9.dist-info/WHEEL
super_analysis-0.1.9.dist-info/entry_points.txt
super_analysis-0.1.9.dist-info/top_level.txt
super_analysis-0.1.9.dist-info/RECORD
