Metadata-Version: 2.1
Name: super-analysis
Version: 0.1.9
Summary: A package for super analysis with ByzerLLM
Home-page: https://github.com/yourusername/super-analysis
Author: allwefantasy
Author-email: allwefantasy@gmail.com
Classifier: Programming Language :: Python :: 3
Classifier: License :: OSI Approved :: MIT License
Classifier: Operating System :: OS Independent
Requires-Python: >=3.6
Requires-Dist: auto-coder
